{
  "method": "CMA-ES",
  "dim": 24,
  "eval_budget": 600,
  "total_evals": 600,
  "popsize": 16,
  "mu": 8,
  "sigma0": 12.0,
  "sigma_final": 50.0,
  "generations": 37,
  "cc": 0.14792959150541557,
  "cs": 0.2021492209000145,
  "c1": 0.0031011073512389447,
  "cmu": 0.008952126627794184,
  "damps": 1.2021492209000144,
  "history": [
    {
      "gen": 1,
      "eval": 16,
      "best_score": -1770.6666564941406,
      "mean_fitness": -2738.5347224473953,
      "sigma": 11.269479083090129
    },
    {
      "gen": 2,
      "eval": 32,
      "best_score": -1172.6666717529297,
      "mean_fitness": -2227.847226381302,
      "sigma": 11.11991846438833
    },
    {
      "gen": 3,
      "eval": 48,
      "best_score": -1084.444450378418,
      "mean_fitness": -1670.8541626930237,
      "sigma": 11.153878787613587
    },
    {
      "gen": 4,
      "eval": 64,
      "best_score": -496.77778244018555,
      "mean_fitness": -1634.9861071109772,
      "sigma": 11.744859535475062
    },
    {
      "gen": 5,
      "eval": 80,
      "best_score": -496.77778244018555,
      "mean_fitness": -1154.7013984322548,
      "sigma": 12.347509988893197
    },
    {
      "gen": 6,
      "eval": 96,
      "best_score": -496.77778244018555,
      "mean_fitness": -1006.7569490671158,
      "sigma": 13.421849389687424
    },
    {
      "gen": 7,
      "eval": 112,
      "best_score": -397.7777786254883,
      "mean_fitness": -857.8611118793488,
      "sigma": 14.33089172236799
    },
    {
      "gen": 8,
      "eval": 128,
      "best_score": -280.66666412353516,
      "mean_fitness": -684.4791700839996,
      "sigma": 15.32786328688828
    },
    {
      "gen": 9,
      "eval": 144,
      "best_score": -280.66666412353516,
      "mean_fitness": -625.8541659116745,
      "sigma": 16.379952985423607
    },
    {
      "gen": 10,
      "eval": 160,
      "best_score": -280.66666412353516,
      "mean_fitness": -660.8472227454185,
      "sigma": 17.502192062970764
    },
    {
      "gen": 11,
      "eval": 176,
      "best_score": -280.66666412353516,
      "mean_fitness": -765.8263862729073,
      "sigma": 18.2886202448911
    },
    {
      "gen": 12,
      "eval": 192,
      "best_score": -280.66666412353516,
      "mean_fitness": -790.513890504837,
      "sigma": 18.90493660915048
    },
    {
      "gen": 13,
      "eval": 208,
      "best_score": -280.66666412353516,
      "mean_fitness": -691.5833376646042,
      "sigma": 19.84267826263317
    },
    {
      "gen": 14,
      "eval": 224,
      "best_score": -280.66666412353516,
      "mean_fitness": -632.437500834465,
      "sigma": 21.19878135305758
    },
    {
      "gen": 15,
      "eval": 240,
      "best_score": -280.66666412353516,
      "mean_fitness": -710.9097217917442,
      "sigma": 22.31943612515947
    },
    {
      "gen": 16,
      "eval": 256,
      "best_score": -280.66666412353516,
      "mean_fitness": -801.4722264409065,
      "sigma": 23.521178438317005
    },
    {
      "gen": 17,
      "eval": 272,
      "best_score": -280.66666412353516,
      "mean_fitness": -730.118058681488,
      "sigma": 24.518783676437508
    },
    {
      "gen": 18,
      "eval": 288,
      "best_score": -280.66666412353516,
      "mean_fitness": -917.2222213745117,
      "sigma": 25.284324090305535
    },
    {
      "gen": 19,
      "eval": 304,
      "best_score": -280.66666412353516,
      "mean_fitness": -1019.8541651368141,
      "sigma": 26.160684573288936
    },
    {
      "gen": 20,
      "eval": 320,
      "best_score": -280.66666412353516,
      "mean_fitness": -977.0347235202789,
      "sigma": 26.796667078216938
    },
    {
      "gen": 21,
      "eval": 336,
      "best_score": -280.66666412353516,
      "mean_fitness": -950.993057847023,
      "sigma": 27.174415514093727
    },
    {
      "gen": 22,
      "eval": 352,
      "best_score": -280.66666412353516,
      "mean_fitness": -1060.8125007748604,
      "sigma": 28.441072343669212
    },
    {
      "gen": 23,
      "eval": 368,
      "best_score": -280.66666412353516,
      "mean_fitness": -1559.0694372653961,
      "sigma": 29.70394324491405
    },
    {
      "gen": 24,
      "eval": 384,
      "best_score": -280.66666412353516,
      "mean_fitness": -1177.215274810791,
      "sigma": 31.988478567738934
    },
    {
      "gen": 25,
      "eval": 400,
      "best_score": -280.66666412353516,
      "mean_fitness": -1306.958330631256,
      "sigma": 34.59353002802924
    },
    {
      "gen": 26,
      "eval": 416,
      "best_score": -280.66666412353516,
      "mean_fitness": -1845.965273976326,
      "sigma": 36.63196849838794
    },
    {
      "gen": 27,
      "eval": 432,
      "best_score": -280.66666412353516,
      "mean_fitness": -1463.319439560175,
      "sigma": 38.663143188990524
    },
    {
      "gen": 28,
      "eval": 448,
      "best_score": -280.66666412353516,
      "mean_fitness": -1298.770832657814,
      "sigma": 40.44912353670649
    },
    {
      "gen": 29,
      "eval": 464,
      "best_score": -280.66666412353516,
      "mean_fitness": -1982.3541714549065,
      "sigma": 42.0603543280122
    },
    {
      "gen": 30,
      "eval": 480,
      "best_score": -280.66666412353516,
      "mean_fitness": -2094.4444407224655,
      "sigma": 43.31306885371511
    },
    {
      "gen": 31,
      "eval": 496,
      "best_score": -280.66666412353516,
      "mean_fitness": -2573.555557012558,
      "sigma": 46.49609519917538
    },
    {
      "gen": 32,
      "eval": 512,
      "best_score": -280.66666412353516,
      "mean_fitness": -2242.4374899864197,
      "sigma": 49.9185912855133
    },
    {
      "gen": 33,
      "eval": 528,
      "best_score": -280.66666412353516,
      "mean_fitness": -1739.3958387970924,
      "sigma": 50.0
    },
    {
      "gen": 34,
      "eval": 544,
      "best_score": -280.66666412353516,
      "mean_fitness": -2763.7639145851135,
      "sigma": 50.0
    },
    {
      "gen": 35,
      "eval": 560,
      "best_score": -280.66666412353516,
      "mean_fitness": -2179.3819415569305,
      "sigma": 50.0
    },
    {
      "gen": 36,
      "eval": 576,
      "best_score": -280.66666412353516,
      "mean_fitness": -2254.902776479721,
      "sigma": 50.0
    },
    {
      "gen": 37,
      "eval": 592,
      "best_score": -280.66666412353516,
      "mean_fitness": -2464.3472154140472,
      "sigma": 50.0
    },
    {
      "eval": 593,
      "phase": "tail_local",
      "score": -901.5555572509766
    },
    {
      "eval": 594,
      "phase": "tail_local",
      "score": -587.9999980926514
    },
    {
      "eval": 595,
      "phase": "tail_local",
      "score": -615.8888854980469
    },
    {
      "eval": 596,
      "phase": "tail_local",
      "score": -308.55555725097656
    },
    {
      "eval": 597,
      "phase": "tail_local",
      "score": -513.3333282470703
    },
    {
      "eval": 598,
      "phase": "tail_local",
      "score": -601.444450378418
    },
    {
      "eval": 599,
      "phase": "tail_local",
      "score": -719.9999961853027
    },
    {
      "eval": 600,
      "phase": "tail_local",
      "score": -431.4444389343262
    }
  ]
}